
    <SampleSet id="samples">

        <!-- if we want to represent a plate, this is how it would be done -->
        <Sample name="My Plate" sampleID="plate1" containerType="96 wells" barcode="b987654">
        </Sample>

        <!-- containerID references the sampleID of the plate -->
        <Sample sampleID="s1" barcode="s1" name="Blank" locationInContainer="A1" containerID="plate1">
        </Sample>​

        <Sample sampleID="s2" barcode="s2" name="Sample 2" locationInContainer="A2" containerID="plate1">
        </Sample>​

        <Sample sampleID="s3" barcode="s3" name="Sample 3" locationInContainer="A3" containerID="plate1">
        </Sample>​

        <Sample sampleID="s4" barcode="s4" name="Sample 4" locationInContainer="A4" containerID="plate1">
        </Sample>​
    </SampleSet>


    <ExperimentStepSet>
        <ExperimentStep name="Bioanalysis" experimentStepID="e1">

            <!-- worklist-level parameters -->
            <Method>
                <Author userType="human">
                    <Name>Hamza</Name>
                </Author>

                <Category name="Worklist Information">
                    <Parameter name="Project" parameterType="String">
                        <S>My Study Name</S>
                    </Parameter>
                    <Parameter name="Batch Name" parameterType="String">
                        <S>My Batch Name</S>
                    </Parameter>
                </Category>
            </Method>

            <!-- results will go here -->
            <Result name="Analytical Result">
                <SeriesSet name="Result Table" length="8">

                    <!-- list of sample names -->
                    <Series name="Sample Name" dependency="dependent" seriesID="s1" seriesType="String"><IndividualValueSet>
                        <S>Blank</S>
                        <S>Blank</S>
                        <S>Sample 2</S>
                        <S>Sample 2</S>
                        <S>Sample 3</S>
                        <S>Sample 3</S>
                        <S>Sample 4</S>
                        <S>Sample 4</S>
                    </IndividualValueSet></Series>

                    <!-- analyte names to correspond with the sample names -->
                    <Series name="Analyte Name" dependency="dependent" seriesID="s2" seriesType="String"><IndividualValueSet>
                        <S>minoxidol</S>
                        <S>carbamazepine</S>
                        <S>minoxidol</S>
                        <S>carbamazepine</S>
                        <S>minoxidol</S>
                        <S>carbamazepine</S>
                        <S>minoxidol</S>
                        <S>carbamazepine</S>
                    </IndividualValueSet></Series>

                    <Series name="Peak Area %" dependency="dependent" seriesID="s3" seriesType="Float32"><IndividualValueSet>
                        <F>12.2</F>
                        <F>17.4</F>
                        <F>12.3</F>
                        <F>17.1</F>
                        <F>12.6</F>
                        <F>17.7</F>
                        <F>24.6</F>
                        <F>21.7</F>
                    </IndividualValueSet></Series>

                    <!-- additional columns go here -->
                </SeriesSet>
            </Result>
        </ExperimentStep>
    </ExperimentStepSet>
